[
  {
    "id": "NbC43ZMhRaZZ8tZ5kbA9G",
    "name": "Three Notes Ascending Descending",
    "notes": [
      {
        "scaleDegree": "I",
        "noteDuration": "8n",
        "isTarget": false
      },
      {
        "scaleDegree": "II",
        "noteDuration": "8n",
        "isTarget": false
      },
      {
        "scaleDegree": "III",
        "noteDuration": "8n",
        "isTarget": false
      },
      {
        "scaleDegree": "II",
        "noteDuration": "8n",
        "isTarget": false
      },
      {
        "scaleDegree": "I",
        "noteDuration": "4n",
        "isTarget": true
      }
    ],
    "version": "2025-10-18T19:52:34.602Z"
  },
  {
    "id": "q6VQ_Cleehoo0AiAXqy4W",
    "name": "Three Notes Descending Ascending",
    "notes": [
      {
        "scaleDegree": "III",
        "noteDuration": "8n",
        "isTarget": false
      },
      {
        "scaleDegree": "II",
        "noteDuration": "8n",
        "isTarget": false
      },
      {
        "scaleDegree": "I",
        "noteDuration": "8n",
        "isTarget": false
      },
      {
        "scaleDegree": "II",
        "noteDuration": "8n",
        "isTarget": false
      },
      {
        "scaleDegree": "I",
        "noteDuration": "4n",
        "isTarget": true
      }
    ],
    "version": "2025-10-18T19:52:34.602Z"
  },
  {
    "id": "_n933jN8J9bwKO5sv7WS1",
    "name": "Three Notes Ascending",
    "notes": [
      {
        "scaleDegree": "-2",
        "noteDuration": "8n",
        "isTarget": false,
        "velocity": 70
      },
      {
        "scaleDegree": "-1",
        "noteDuration": "8n",
        "isTarget": false,
        "velocity": 70
      },
      {
        "scaleDegree": "I",
        "noteDuration": "8n",
        "isTarget": true,
        "velocity": 90
      }
    ],
    "version": "2025-10-18T19:52:34.602Z"
  },
  {
    "id": "5oJKogu0ht2-kyN2m5JHg",
    "name": "Single Note Octaves",
    "notes": [
      {
        "scaleDegree": "-I",
        "noteDuration": "4n",
        "isTarget": false,
        "velocity": 70
      },
      {
        "scaleDegree": "I",
        "noteDuration": "4n",
        "isTarget": false,
        "velocity": 70
      },
      {
        "scaleDegree": "+I",
        "noteDuration": "4n",
        "isTarget": true,
        "velocity": 90
      }
    ],
    "version": "2025-10-18T19:52:34.602Z"
  },
  {
    "id": "OkpHgnG1bUbumAVYpPa8t",
    "name": "Abdo Dagher 1",
    "notes": [
      {
        "scaleDegree": "I",
        "noteDuration": "8n",
        "isTarget": true,
        "velocity": 90
      },
      {
        "scaleDegree": "II",
        "noteDuration": "16n",
        "isTarget": false,
        "velocity": 70
      },
      {
        "scaleDegree": "I",
        "noteDuration": "16n",
        "isTarget": false,
        "velocity": 70
      },
      {
        "scaleDegree": "-1",
        "noteDuration": "8n",
        "isTarget": false,
        "velocity": 70
      },
      {
        "scaleDegree": "I",
        "noteDuration": "8n",
        "isTarget": false,
        "velocity": 70
      }
    ],
    "version": "2025-10-18T19:52:34.602Z"
  },
  {
    "id": "Vwgo4te4XXOwcHxQdoiBj",
    "name": "Three Notes Descending",
    "notes": [
      {
        "scaleDegree": "III",
        "noteDuration": "8n",
        "isTarget": false
      },
      {
        "scaleDegree": "II",
        "noteDuration": "8n",
        "isTarget": false
      },
      {
        "scaleDegree": "I",
        "noteDuration": "8n",
        "isTarget": true
      }
    ],
    "version": "2025-10-18T19:52:34.602Z"
  },
  {
    "id": "NnoF7nBwVtt3pdsevNZRr",
    "name": "Default",
    "notes": [
      {
        "scaleDegree": "I",
        "noteDuration": "8n",
        "isTarget": false,
        "velocity": 90
      },
      {
        "scaleDegree": "-1",
        "noteDuration": "8n",
        "isTarget": false,
        "velocity": 70
      },
      {
        "scaleDegree": "I",
        "noteDuration": "8n",
        "isTarget": true,
        "velocity": 90
      }
    ],
    "version": "2025-10-18T19:52:34.602Z"
  }
]